vcstool/__init__.py
vcstool/crawler.py
vcstool/executor.py
vcstool/streams.py
vcstool/util.py
vcstool/clients/__init__.py
vcstool/clients/bzr.py
vcstool/clients/git.py
vcstool/clients/hg.py
vcstool/clients/none.py
vcstool/clients/svn.py
vcstool/clients/tar.py
vcstool/clients/vcs_base.py
vcstool/clients/zip.py
vcstool/commands/__init__.py
vcstool/commands/branch.py
vcstool/commands/command.py
vcstool/commands/custom.py
vcstool/commands/diff.py
vcstool/commands/export.py
vcstool/commands/help.py
vcstool/commands/import_.py
vcstool/commands/log.py
vcstool/commands/pull.py
vcstool/commands/push.py
vcstool/commands/remotes.py
vcstool/commands/status.py
vcstool/commands/validate.py
vcstool/commands/vcs.py
vcstool/compat/__init__.py
vcstool/compat/shutil.py
vcstool-0.2.15.data/data/share/vcstool-completion/vcs.bash
vcstool-0.2.15.data/data/share/vcstool-completion/vcs.tcsh
vcstool-0.2.15.data/data/share/vcstool-completion/vcs.zsh
vcstool-0.2.15.dist-info/LICENSE
vcstool-0.2.15.dist-info/METADATA
vcstool-0.2.15.dist-info/WHEEL
vcstool-0.2.15.dist-info/entry_points.txt
vcstool-0.2.15.dist-info/top_level.txt
vcstool-0.2.15.dist-info/RECORD
